superdiff/__init__.py
superdiff/differ.py
superdiff/parser.py
superdiff-1.0.1.dist-info/DESCRIPTION.rst
superdiff-1.0.1.dist-info/METADATA
superdiff-1.0.1.dist-info/RECORD
superdiff-1.0.1.dist-info/WHEEL
superdiff-1.0.1.dist-info/metadata.json
superdiff-1.0.1.dist-info/top_level.txt
