Metadata-Version: 2.0
Name: superdiff
Version: 1.0.1
Summary: A library for performing flexible diff checks.
Home-page: https://github.com/james-perretta/superdiff
Author: James Perretta
Author-email: jameslp@umich.edu
License: GNU Lesser General Public License v3
Platform: UNKNOWN
Classifier: Programming Language :: Python :: 3.5
